lalang/__init__.py
lalang/__main__.py
lalang/config.py
lalang/grammar.py
lalang/huruf.py
lalang/keywords.py
lalang/lalang.py
lalang/searchable.py
lalang/snippets.py
lalang/item_block/__init__.py
lalang/item_block/anonymous_function.py
lalang/item_block/class_item.py
lalang/item_block/constructor_content.py
lalang/item_block/exception_item.py
lalang/item_block/field_content.py
lalang/item_block/function_item.py
lalang/item_block/interface_item.py
lalang/item_block/method_content.py
lalang/item_block/scope_item.py
lalang/item_export/__init__.py
lalang/item_expression/__init__.py
lalang/item_expression/function_call.py
lalang/item_expression/literal.py
lalang/item_expression/match_expression.py
lalang/item_expression/operator.py
lalang/item_expression/range_expression.py
lalang/item_import/__init__.py
lalang/item_package/__init__.py
lalang/item_statement/__init__.py
lalang/item_statement/assignment_statement.py
lalang/item_statement/condition_body.py
lalang/item_statement/const_declaration.py
lalang/item_statement/declaration_config.py
lalang/item_statement/destructuring_statement.py
lalang/item_statement/enum_declaration.py
lalang/item_statement/for_statement.py
lalang/item_statement/if_statement.py
lalang/item_statement/single_statement.py
lalang/item_statement/switch_statement.py
lalang/item_statement/typealias_declaration.py
lalang/item_statement/var_declaration.py
lalang/item_statement/while_statement.py
lalang/zgenerate/__init__.py
lalang/zgenerate/common.py
lalang/zgenerate/gen_cpp.py
lalang/zgenerate/gen_cs.py
lalang/zgenerate/gen_dart.py
lalang/zgenerate/gen_elixir.py
lalang/zgenerate/gen_go.py
lalang/zgenerate/gen_java.py
lalang/zgenerate/gen_kt.py
lalang/zgenerate/gen_py.py
lalang/zgenerate/gen_rb.py
lalang/zgenerate/gen_rs.py
lalang/zgenerate/gen_scala.py
lalang/zgenerate/gen_ts.py
lalang/zgenerate/gen_v.py
lalang/zgenerate/helper/fmus_helper.py
lalang/zgenerate/helper/gui_helper.py
lalang/zgenerate/helper/react_helper.py
lalang-0.0.1.dist-info/LICENSE
lalang-0.0.1.dist-info/METADATA
lalang-0.0.1.dist-info/WHEEL
lalang-0.0.1.dist-info/top_level.txt
lalang-0.0.1.dist-info/RECORD
