Metadata-Version: 2.1
Name: lalang
Version: 0.0.1
Summary: Lazy programmer's own language
Author-email: yusef <yusef314159@gmail.com>
License: Copyright (c) 2018 The Python Packaging Authority        
Project-URL: Homepage, https://github.com/uulum/lalang
Project-URL: Bug Tracker, https://github.com/uulum/lalang/issues
Classifier: Programming Language :: Python :: 3
Classifier: License :: OSI Approved :: MIT License
Classifier: Operating System :: OS Independent
Requires-Python: >=3.9
License-File: LICENSE
Requires-Dist: yulibrary
Requires-Dist: declang
